image2gcode/__init__.py
image2gcode/__main__.py
image2gcode/boundingbox.py
image2gcode/image2gcode.py
image2gcode/imagegen.py
image2gcode/newimage2gcode.py
image2gcode-2.9.14.dist-info/entry_points.txt
image2gcode-2.9.14.dist-info/licenses/LICENSE
image2gcode-2.9.14.dist-info/WHEEL
image2gcode-2.9.14.dist-info/METADATA
image2gcode-2.9.14.dist-info/RECORD
