Metadata-Version: 2.4
Name: image2gcode
Version: 2.9.14
Summary: image2gcode: convert an image to gcode.
Keywords: engraving,laser,image,laser engraving,PWM,gcode
Author-email: Johannes Noordanus <mailjohannes.mailnoordanus@gmail.com>
Requires-Python: >=3.7
Classifier: License :: OSI Approved :: MIT License
License-File: LICENSE
Requires-Dist: gcode2image >= 2.3.1
Requires-Dist: numpy >= 1.24.3
Requires-Dist: Pillow >= 9.5.0
Requires-Dist: nptyping >= 2.0.0
Project-URL: Home, https://github.com/johannesnoordanus/image2gcode
